Metadata-Version: 1.0
Name: mongodbModel
Version: 2.1.0
Summary: mongodbModel
Home-page: UNKNOWN
Author: donglidunyin
Author-email: donglidunyin@163.com
License: UNKNOWN
Platform: UNKNOWN
